<annotation>
	<folder>collectedimages</folder>
	<filename>V.ac531f2c-590a-11ec-9140-4074e0a6c763.jpg</filename>
	<path>E:\all program\ggProject\RealTimeObjectDetection\Tensorflow\workspace\images\collectedimages\V.ac531f2c-590a-11ec-9140-4074e0a6c763.jpg</path>
	<source>
		<database>Unknown</database>
	</source>
	<size>
		<width>640</width>
		<height>480</height>
		<depth>3</depth>
	</size>
	<segmented>0</segmented>
	<object>
		<name>V</name>
		<pose>Unspecified</pose>
		<truncated>0</truncated>
		<difficult>0</difficult>
		<bndbox>
			<xmin>197</xmin>
			<ymin>206</ymin>
			<xmax>341</xmax>
			<ymax>439</ymax>
		</bndbox>
	</object>
</annotation>
